svg/__init__.py
svg/path/__init__.py
svg/path/parser.py
svg/path/path.py
svg.path-6.3.dist-info/LICENSE.txt
svg.path-6.3.dist-info/METADATA
svg.path-6.3.dist-info/WHEEL
svg.path-6.3.dist-info/top_level.txt
svg.path-6.3.dist-info/zip-safe
svg.path-6.3.dist-info/RECORD
