Metadata-Version: 2.1
Name: svg.path
Version: 6.3
Summary: SVG path objects and parser
Home-page: https://github.com/regebro/svg.path
Author: Lennart Regebro
Author-email: regebro@gmail.com
License: MIT
Keywords: svg,path,maths
Platform: UNKNOWN
Classifier: Development Status :: 5 - Production/Stable
Classifier: Intended Audience :: Developers
Classifier: License :: OSI Approved :: MIT License
Classifier: Operating System :: OS Independent
Classifier: Programming Language :: Python
Classifier: Programming Language :: Python :: 3
Classifier: Programming Language :: Python :: 3.8
Classifier: Programming Language :: Python :: 3.9
Classifier: Programming Language :: Python :: 3.10
Classifier: Programming Language :: Python :: 3.11
Classifier: Programming Language :: Python :: 3 :: Only
Classifier: Programming Language :: Python :: Implementation :: PyPy
Classifier: Topic :: Multimedia :: Graphics
Requires-Python: >=3.8
Provides-Extra: test
License-File: LICENSE.txt
